gpt_pdf_md/__init__.py
gpt_pdf_md/reader.py
gpt_pdf_md-0.3.dist-info/LICENSE
gpt_pdf_md-0.3.dist-info/METADATA
gpt_pdf_md-0.3.dist-info/WHEEL
gpt_pdf_md-0.3.dist-info/top_level.txt
gpt_pdf_md-0.3.dist-info/RECORD
